stdout_stderr_capturing/__init__.py
stdout_stderr_capturing/py.typed
stdout_stderr_capturing-0.2.1.dist-info/LICENSE
stdout_stderr_capturing-0.2.1.dist-info/METADATA
stdout_stderr_capturing-0.2.1.dist-info/WHEEL
stdout_stderr_capturing-0.2.1.dist-info/RECORD
