Metadata-Version: 2.1
Name: stdout_stderr_capturing
Version: 0.2.1
Summary: Capture the stdout or stderr output as a list in a context manager block (with).
Home-page: https://github.com/Josef-Friedrich/stdout_stderr_capturing
License: MIT
Author: Josef Friedrich
Author-email: josef@friedrich.rocks
Requires-Python: >=3.10,<4.0
Classifier: Development Status :: 5 - Production/Stable
Classifier: License :: OSI Approved :: MIT License
Classifier: Programming Language :: Python :: 3
Classifier: Programming Language :: Python :: 3.10
Classifier: Programming Language :: Python :: 3.11
Classifier: Programming Language :: Python :: 3.12
Classifier: Programming Language :: Python :: 3 :: Only
Project-URL: Repository, https://github.com/Josef-Friedrich/stdout_stderr_capturing
